Workbook

Sheet Synthèse
A1: Clubify — suivi des features
A2: Généré par tools/generer-suivi.py depuis docs/couverture-backlog.md et docs/roadmap.md. Les états et les dates se saisissent dans la feuille Features ; les feuilles par release les reprennent.
A5: Release | B5: Nom | C5: Fenêtre de mise en service | D5: Features | E5: Waiting | F5: Cadrage | G5: Dev | H5: In test | I5: Production | J5: % terminé | K5: Identifiants
A6: R1 | B6: Comptoir | C6: janvier 2027, entrées en cours de saison | D6: =COUNTIF(Features!$C$2:$C$74,$A6) | E6: =COUNTIFS(Features!$C$2:$C$74,$A6,Features!$F$2:$F$74,"Waiting") | F6: =COUNTIFS(Features!$C$2:$C$74,$A6,Features!$F$2:$F$74,"Cadrage") | G6: =COUNTIFS(Features!$C$2:$C$74,$A6,Features!$F$2:$F$74,"Dev") | H6: =COUNTIFS(Features!$C$2:$C$74,$A6,Features!$F$2:$F$74,"In test") | I6: =COUNTIFS(Features!$C$2:$C$74,$A6,Features!$F$2:$F$74,"Production") | J6: =IF($D6=0,"",$I6/$D6) | K6: 72
A7: R2 | B7: Planning et coachs | C7: avril 2027, en service au plus tard en juillet 2027 pour préparer la saison 2027-2028 (duplication de saison, groupes, créneaux) | D7: =COUNTIF(Features!$C$2:$C$74,$A7) | E7: =COUNTIFS(Features!$C$2:$C$74,$A7,Features!$F$2:$F$74,"Waiting") | F7: =COUNTIFS(Features!$C$2:$C$74,$A7,Features!$F$2:$F$74,"Cadrage") | G7: =COUNTIFS(Features!$C$2:$C$74,$A7,Features!$F$2:$F$74,"Dev") | H7: =COUNTIFS(Features!$C$2:$C$74,$A7,Features!$F$2:$F$74,"In test") | I7: =COUNTIFS(Features!$C$2:$C$74,$A7,Features!$F$2:$F$74,"Production") | J7: =IF($D7=0,"",$I7/$D7) | K7: 18
A8: R3 | B8: Parents, relances et exports comptables | C8: mai-juin 2027 pour relancer les reliquats de fin de saison et couvrir la cérémonie de juin ; au plus tard septembre 2027 pour les échéanciers du pic | D8: =COUNTIF(Features!$C$2:$C$74,$A8) | E8: =COUNTIFS(Features!$C$2:$C$74,$A8,Features!$F$2:$F$74,"Waiting") | F8: =COUNTIFS(Features!$C$2:$C$74,$A8,Features!$F$2:$F$74,"Cadrage") | G8: =COUNTIFS(Features!$C$2:$C$74,$A8,Features!$F$2:$F$74,"Dev") | H8: =COUNTIFS(Features!$C$2:$C$74,$A8,Features!$F$2:$F$74,"In test") | I8: =COUNTIFS(Features!$C$2:$C$74,$A8,Features!$F$2:$F$74,"Production") | J8: =IF($D8=0,"",$I8/$D8) | K8: 23
A9: R4 | B9: Pointage | C9: septembre 2027, premier cours de la saison 2027-2028, pour que les coachs prennent l'habitude dès le départ | D9: =COUNTIF(Features!$C$2:$C$74,$A9) | E9: =COUNTIFS(Features!$C$2:$C$74,$A9,Features!$F$2:$F$74,"Waiting") | F9: =COUNTIFS(Features!$C$2:$C$74,$A9,Features!$F$2:$F$74,"Cadrage") | G9: =COUNTIFS(Features!$C$2:$C$74,$A9,Features!$F$2:$F$74,"Dev") | H9: =COUNTIFS(Features!$C$2:$C$74,$A9,Features!$F$2:$F$74,"In test") | I9: =COUNTIFS(Features!$C$2:$C$74,$A9,Features!$F$2:$F$74,"Production") | J9: =IF($D9=0,"",$I9/$D9) | K9: 16
A10: R5 | B10: Rémunération et arrière-boutique | C10: novembre 2027 à janvier 2028, après un mois complet de séances pointées | D10: =COUNTIF(Features!$C$2:$C$74,$A10) | E10: =COUNTIFS(Features!$C$2:$C$74,$A10,Features!$F$2:$F$74,"Waiting") | F10: =COUNTIFS(Features!$C$2:$C$74,$A10,Features!$F$2:$F$74,"Cadrage") | G10: =COUNTIFS(Features!$C$2:$C$74,$A10,Features!$F$2:$F$74,"Dev") | H10: =COUNTIFS(Features!$C$2:$C$74,$A10,Features!$F$2:$F$74,"In test") | I10: =COUNTIFS(Features!$C$2:$C$74,$A10,Features!$F$2:$F$74,"Production") | J10: =IF($D10=0,"",$I10/$D10) | K10: 18
A11: R6 | B11: Fin de saison et réinscription | C11: mars-avril 2028, pour la campagne de mai-juin 2028 et la cérémonie de juin 2028 | D11: =COUNTIF(Features!$C$2:$C$74,$A11) | E11: =COUNTIFS(Features!$C$2:$C$74,$A11,Features!$F$2:$F$74,"Waiting") | F11: =COUNTIFS(Features!$C$2:$C$74,$A11,Features!$F$2:$F$74,"Cadrage") | G11: =COUNTIFS(Features!$C$2:$C$74,$A11,Features!$F$2:$F$74,"Dev") | H11: =COUNTIFS(Features!$C$2:$C$74,$A11,Features!$F$2:$F$74,"In test") | I11: =COUNTIFS(Features!$C$2:$C$74,$A11,Features!$F$2:$F$74,"Production") | J11: =IF($D11=0,"",$I11/$D11) | K11: 13
A12: R7 | B12: Camp d'été | C12: mai 2028 pour le camp de juillet 2028 | D12: =COUNTIF(Features!$C$2:$C$74,$A12) | E12: =COUNTIFS(Features!$C$2:$C$74,$A12,Features!$F$2:$F$74,"Waiting") | F12: =COUNTIFS(Features!$C$2:$C$74,$A12,Features!$F$2:$F$74,"Cadrage") | G12: =COUNTIFS(Features!$C$2:$C$74,$A12,Features!$F$2:$F$74,"Dev") | H12: =COUNTIFS(Features!$C$2:$C$74,$A12,Features!$F$2:$F$74,"In test") | I12: =COUNTIFS(Features!$C$2:$C$74,$A12,Features!$F$2:$F$74,"Production") | J12: =IF($D12=0,"",$I12/$D12) | K12: 6
A13: R8 | B13: Portail parent et acquisition | C13: septembre 2028, les parents découvrent le portail à l'inscription | D13: =COUNTIF(Features!$C$2:$C$74,$A13) | E13: =COUNTIFS(Features!$C$2:$C$74,$A13,Features!$F$2:$F$74,"Waiting") | F13: =COUNTIFS(Features!$C$2:$C$74,$A13,Features!$F$2:$F$74,"Cadrage") | G13: =COUNTIFS(Features!$C$2:$C$74,$A13,Features!$F$2:$F$74,"Dev") | H13: =COUNTIFS(Features!$C$2:$C$74,$A13,Features!$F$2:$F$74,"In test") | I13: =COUNTIFS(Features!$C$2:$C$74,$A13,Features!$F$2:$F$74,"Production") | J13: =IF($D13=0,"",$I13/$D13) | K13: 20
A14: R9 | B14: Deuxième club | C14: aucune fenêtre calendaire ; déclenchée par la signature d'un second club | D14: =COUNTIF(Features!$C$2:$C$74,$A14) | E14: =COUNTIFS(Features!$C$2:$C$74,$A14,Features!$F$2:$F$74,"Waiting") | F14: =COUNTIFS(Features!$C$2:$C$74,$A14,Features!$F$2:$F$74,"Cadrage") | G14: =COUNTIFS(Features!$C$2:$C$74,$A14,Features!$F$2:$F$74,"Dev") | H14: =COUNTIFS(Features!$C$2:$C$74,$A14,Features!$F$2:$F$74,"In test") | I14: =COUNTIFS(Features!$C$2:$C$74,$A14,Features!$F$2:$F$74,"Production") | J14: =IF($D14=0,"",$I14/$D14) | K14: 4
A15: Total | D15: =SUM(D6:D14) | E15: =SUM(E6:E14) | F15: =SUM(F6:F14) | G15: =SUM(G6:G14) | H15: =SUM(H6:H14) | I15: =SUM(I6:I14) | J15: =IF($D15=0,"",$I15/$D15) | K15: =SUM(K6:K14)
A17: 13 identifiants écartés, voir la feuille Écartés.
A19: États
A20: Waiting | B20: Pas commencée
A21: Cadrage | B21: Étapes 1 et 2 : fiche, questions, benchmark
A22: Dev | B22: Étapes 3 à 5 : plan, tests d'abord, implémentation
A23: In test | B23: Étape 5 : tests verts, recette
A24: Production | B24: Étape 6 : livrée, validée, en service
A26: Dates
A27: Cycle de développement : de « Début cadrage » à « Fin test ».
A28: Mise en production : colonne « Date production », distincte du cycle.

Sheet Features
A1: Feature | B1: Nom | C1: Release | D1: Identifiants du backlog | E1: Nb ID | F1: État | G1: Responsable | H1: Début cadrage | I1: Fin cadrage | J1: Début dev | K1: Fin dev | L1: Début test | M1: Fin test | N1: Durée cycle (j) | O1: Date production | P1: Délai test → prod (j) | Q1: Commentaire
A2: F01 | B2: Socle plateforme | C2: R1 | D2: PLT-01, PLT-04, PLT-05, SEC-01, SEC-02, SEC-03, SEC-04, ADM-01, INT-03 | E2: 9 | F2: Cadrage | H2: 46285 | N2: =IF(AND(H2<>"",M2<>""),M2-H2,"") | P2: =IF(AND(M2<>"",O2<>""),O2-M2,"") | Q2: Fiche rédigée, 10 questions en attente
A3: F02 | B3: Famille, parents, enfant | C3: R1 | D3: FAM-01, FAM-02, FAM-03, FAM-04, FAM-12 | E3: 5 | F3: Waiting | N3: =IF(AND(H3<>"",M3<>""),M3-H3,"") | P3: =IF(AND(M3<>"",O3<>""),O3-M3,"")
A4: F03 | B4: Dossier complet | C4: R1 | D4: FAM-05, FAM-06, FAM-07, FAM-08, FAM-11, ONB-03, ONB-04, ADM-04 | E4: 8 | F4: Waiting | N4: =IF(AND(H4<>"",M4<>""),M4-H4,"") | P4: =IF(AND(M4<>"",O4<>""),O4-M4,"")
A5: F04 | B5: Catalogue, groupes, saison | C5: R1 | D5: ACT-01, ACT-02, ACT-03, ACT-04, NIV-01, GRP-01, GRP-03, GRP-04, PLA-01, PLA-02, PLA-05 | E5: 11 | F5: Waiting | N5: =IF(AND(H5<>"",M5<>""),M5-H5,"") | P5: =IF(AND(M5<>"",O5<>""),O5-M5,"")
A6: F05 | B6: Offre et grille tarifaire | C6: R1 | D6: OFR-01, OFR-02, OFR-03, OFR-04, OFR-05, TAR-01, TAR-02, TAR-03, TAR-06, TAR-08 | E6: 10 | F6: Waiting | N6: =IF(AND(H6<>"",M6<>""),M6-H6,"") | P6: =IF(AND(M6<>"",O6<>""),O6-M6,"")
A7: F06 | B7: Remises | C7: R1 | D7: TAR-04, TAR-05 | E7: 2 | F7: Waiting | N7: =IF(AND(H7<>"",M7<>""),M7-H7,"") | P7: =IF(AND(M7<>"",O7<>""),O7-M7,"")
A8: F07 | B8: Inscription | C8: R1 | D8: INS-01, INS-02, INS-03, GRP-02, GRP-05, FAM-10, ONB-01, ONB-05 | E8: 8 | F8: Waiting | N8: =IF(AND(H8<>"",M8<>""),M8-H8,"") | P8: =IF(AND(M8<>"",O8<>""),O8-M8,"")
A9: F08 | B9: Facture famille et solde | C9: R1 | D9: FAC-01, FAC-02, FAC-06, FAC-09, CPT-02 | E9: 5 | F9: Waiting | N9: =IF(AND(H9<>"",M9<>""),M9-H9,"") | P9: =IF(AND(M9<>"",O9<>""),O9-M9,"")
A10: F09 | B10: Encaissement et reçu | C10: R1 | D10: FAC-03, FAC-05, FAC-07, FIN-04 | E10: 4 | F10: Waiting | N10: =IF(AND(H10<>"",M10<>""),M10-H10,"") | P10: =IF(AND(M10<>"",O10<>""),O10-M10,"")
A11: F10 | B11: Registre des chèques | C11: R1 | D11: FAC-08 | E11: 1 | F11: Waiting | N11: =IF(AND(H11<>"",M11<>""),M11-H11,"") | P11: =IF(AND(M11<>"",O11<>""),O11-M11,"")
A12: F11 | B12: Avoir et remboursement | C12: R1 | D12: FAC-04 | E12: 1 | F12: Waiting | N12: =IF(AND(H12<>"",M12<>""),M12-H12,"") | P12: =IF(AND(M12<>"",O12<>""),O12-M12,"")
A13: F12 | B13: Caisse et remise du jour | C13: R1 | D13: FIN-01, FIN-03 | E13: 2 | F13: Waiting | N13: =IF(AND(H13<>"",M13<>""),M13-H13,"") | P13: =IF(AND(M13<>"",O13<>""),O13-M13,"")
A14: F13 | B14: Dépenses et résultat mensuel | C14: R1 | D14: FIN-02, FIN-05 | E14: 2 | F14: Waiting | N14: =IF(AND(H14<>"",M14<>""),M14-H14,"") | P14: =IF(AND(M14<>"",O14<>""),O14-M14,"")
... A74: F73 | B74: Abonnement SaaS | C74: R9 | D74: PLT-07 | E74: 1 | F74: Waiting | N74: =IF(AND(H74<>"",M74<>""),M74-H74,"") | P74: =IF(AND(M74<>"",O74<>""),O74-M74,"")

Sheet R1
A1: ID | B1: Domaine | C1: Libellé | D1: Cahier | E1: Feature | F1: État | G1: Date production
A2: FAM-01 | B2: Familles / Adhérents | C2: Compte famille | D2: MVP | E2: F02 | F2: =IFERROR(VLOOKUP($E2,Features!$A$2:$Q$74,6,FALSE),"") | G2: =IFERROR(VLOOKUP($E2,Features!$A$2:$Q$74,15,FALSE),"")
A3: FAM-02 | B3: Familles / Adhérents | C3: Parents / tuteurs | D3: MVP | E3: F02 | F3: =IFERROR(VLOOKUP($E3,Features!$A$2:$Q$74,6,FALSE),"") | G3: =IFERROR(VLOOKUP($E3,Features!$A$2:$Q$74,15,FALSE),"")
A4: FAM-03 | B4: Familles / Adhérents | C4: Responsable financier | D4: MVP | E4: F02 | F4: =IFERROR(VLOOKUP($E4,Features!$A$2:$Q$74,6,FALSE),"") | G4: =IFERROR(VLOOKUP($E4,Features!$A$2:$Q$74,15,FALSE),"")
A5: FAM-04 | B5: Familles / Adhérents | C5: Fiche enfant | D5: MVP | E5: F02 | F5: =IFERROR(VLOOKUP($E5,Features!$A$2:$Q$74,6,FALSE),"") | G5: =IFERROR(VLOOKUP($E5,Features!$A$2:$Q$74,15,FALSE),"")
A6: FAM-05 | B6: Familles / Adhérents | C6: Contacts d'urgence | D6: MVP | E6: F03 | F6: =IFERROR(VLOOKUP($E6,Features!$A$2:$Q$74,6,FALSE),"") | G6: =IFERROR(VLOOKUP($E6,Features!$A$2:$Q$74,15,FALSE),"")
A7: FAM-06 | B7: Familles / Adhérents | C7: Personnes autorisées à récupérer | D7: MVP | E7: F03 | F7: =IFERROR(VLOOKUP($E7,Features!$A$2:$Q$74,6,FALSE),"") | G7: =IFERROR(VLOOKUP($E7,Features!$A$2:$Q$74,15,FALSE),"")
A8: FAM-07 | B8: Familles / Adhérents | C8: Fiche santé | D8: MVP | E8: F03 | F8: =IFERROR(VLOOKUP($E8,Features!$A$2:$Q$74,6,FALSE),"") | G8: =IFERROR(VLOOKUP($E8,Features!$A$2:$Q$74,15,FALSE),"")
A9: FAM-08 | B9: Familles / Adhérents | C9: Pièces du dossier | D9: MVP | E9: F03 | F9: =IFERROR(VLOOKUP($E9,Features!$A$2:$Q$74,6,FALSE),"") | G9: =IFERROR(VLOOKUP($E9,Features!$A$2:$Q$74,15,FALSE),"")
A10: FAM-10 | B10: Familles / Adhérents | C10: Statut adhérent | D10: MVP | E10: F07 | F10: =IFERROR(VLOOKUP($E10,Features!$A$2:$Q$74,6,FALSE),"") | G10: =IFERROR(VLOOKUP($E10,Features!$A$2:$Q$74,15,FALSE),"")
A11: FAM-11 | B11: Familles / Adhérents | C11: Vue 360° | D11: MVP | E11: F03 | F11: =IFERROR(VLOOKUP($E11,Features!$A$2:$Q$74,6,FALSE),"") | G11: =IFERROR(VLOOKUP($E11,Features!$A$2:$Q$74,15,FALSE),"")
A12: FAM-12 | B12: Familles / Adhérents | C12: Recherche et filtres | D12: MVP | E12: F02 | F12: =IFERROR(VLOOKUP($E12,Features!$A$2:$Q$74,6,FALSE),"") | G12: =IFERROR(VLOOKUP($E12,Features!$A$2:$Q$74,15,FALSE),"")
A13: FAM-13 | B13: Familles / Adhérents | C13: Import Excel | D13: MVP | E13: F16 | F13: =IFERROR(VLOOKUP($E13,Features!$A$2:$Q$74,6,FALSE),"") | G13: =IFERROR(VLOOKUP($E13,Features!$A$2:$Q$74,15,FALSE),"")
... A73: OFR-05 | B73: Paramétrage de l'offre | C73: Simulateur de prix | D73: MVP | E73: F05 | F73: =IFERROR(VLOOKUP($E73,Features!$A$2:$Q$74,6,FALSE),"") | G73: =IFERROR(VLOOKUP($E73,Features!$A$2:$Q$74,15,FALSE),"")
A75: R1 — Comptoir

Sheet R2
A1: ID | B1: Domaine | C1: Libellé | D1: Cahier | E1: Feature | F1: État | G1: Date production
A2: FAM-09 | B2: Familles / Adhérents | C2: Adhérent adulte | D2: MVP | E2: F23 | F2: =IFERROR(VLOOKUP($E2,Features!$A$2:$Q$74,6,FALSE),"") | G2: =IFERROR(VLOOKUP($E2,Features!$A$2:$Q$74,15,FALSE),"")
A3: GRP-06 | B3: Groupes | C3: Impression du roster | D3: MVP | E3: F20 | F3: =IFERROR(VLOOKUP($E3,Features!$A$2:$Q$74,6,FALSE),"") | G3: =IFERROR(VLOOKUP($E3,Features!$A$2:$Q$74,15,FALSE),"")
A4: PLA-03 | B4: Planning | C4: Génération des séances | D4: MVP | E4: F18 | F4: =IFERROR(VLOOKUP($E4,Features!$A$2:$Q$74,6,FALSE),"") | G4: =IFERROR(VLOOKUP($E4,Features!$A$2:$Q$74,15,FALSE),"")
A5: PLA-04 | B5: Planning | C5: Vues jour, semaine, mois | D5: MVP | E5: F18 | F5: =IFERROR(VLOOKUP($E5,Features!$A$2:$Q$74,6,FALSE),"") | G5: =IFERROR(VLOOKUP($E5,Features!$A$2:$Q$74,15,FALSE),"")
A6: PLA-07 | B6: Planning | C6: Remplacement de coach | D6: MVP | E6: F19 | F6: =IFERROR(VLOOKUP($E6,Features!$A$2:$Q$74,6,FALSE),"") | G6: =IFERROR(VLOOKUP($E6,Features!$A$2:$Q$74,15,FALSE),"")
A7: PLA-08 | B7: Planning | C7: Séance ponctuelle | D7: MVP | E7: F19 | F7: =IFERROR(VLOOKUP($E7,Features!$A$2:$Q$74,6,FALSE),"") | G7: =IFERROR(VLOOKUP($E7,Features!$A$2:$Q$74,15,FALSE),"")
A8: PLA-09 | B8: Planning | C8: Horaires spéciaux | D8: V2 | E8: F19 | F8: =IFERROR(VLOOKUP($E8,Features!$A$2:$Q$74,6,FALSE),"") | G8: =IFERROR(VLOOKUP($E8,Features!$A$2:$Q$74,15,FALSE),"")
A9: PLA-10 | B9: Planning | C9: Planning publiable | D9: V2 | E9: F21 | F9: =IFERROR(VLOOKUP($E9,Features!$A$2:$Q$74,6,FALSE),"") | G9: =IFERROR(VLOOKUP($E9,Features!$A$2:$Q$74,15,FALSE),"")
A10: RES-01 | B10: Réservations | C10: Cours d'essai | D10: MVP | E10: F22 | F10: =IFERROR(VLOOKUP($E10,Features!$A$2:$Q$74,6,FALSE),"") | G10: =IFERROR(VLOOKUP($E10,Features!$A$2:$Q$74,15,FALSE),"")
A11: RES-06 | B11: Réservations | C11: Cours privé | D11: MVP | E11: F23 | F11: =IFERROR(VLOOKUP($E11,Features!$A$2:$Q$74,6,FALSE),"") | G11: =IFERROR(VLOOKUP($E11,Features!$A$2:$Q$74,15,FALSE),"")
A12: INS-07 | B12: Abonnements / Inscriptions | C12: Résiliation | D12: MVP | E12: F24 | F12: =IFERROR(VLOOKUP($E12,Features!$A$2:$Q$74,6,FALSE),"") | G12: =IFERROR(VLOOKUP($E12,Features!$A$2:$Q$74,15,FALSE),"")
A13: INS-08 | B13: Abonnements / Inscriptions | C13: Changement d'activité | D13: MVP | E13: F24 | F13: =IFERROR(VLOOKUP($E13,Features!$A$2:$Q$74,6,FALSE),"") | G13: =IFERROR(VLOOKUP($E13,Features!$A$2:$Q$74,15,FALSE),"")
... A19: OFR-08 | B19: Paramétrage de l'offre | C19: Duplication de saison | D19: V2 | E19: F25 | F19: =IFERROR(VLOOKUP($E19,Features!$A$2:$Q$74,6,FALSE),"") | G19: =IFERROR(VLOOKUP($E19,Features!$A$2:$Q$74,15,FALSE),"")
A21: R2 — Planning et coachs

Sheet R3
A1: ID | B1: Domaine | C1: Libellé | D1: Cahier | E1: Feature | F1: État | G1: Date production
A2: PLA-06 | B2: Planning | C2: Annulation, report | D2: MVP | E2: F28 | F2: =IFERROR(VLOOKUP($E2,Features!$A$2:$Q$74,6,FALSE),"") | G2: =IFERROR(VLOOKUP($E2,Features!$A$2:$Q$74,15,FALSE),"")
A3: INS-04 | B3: Abonnements / Inscriptions | C3: Renouvellement | D3: MVP | E3: F31 | F3: =IFERROR(VLOOKUP($E3,Features!$A$2:$Q$74,6,FALSE),"") | G3: =IFERROR(VLOOKUP($E3,Features!$A$2:$Q$74,15,FALSE),"")
A4: INS-09 | B4: Abonnements / Inscriptions | C4: Alerte d'expiration | D4: MVP | E4: F27 | F4: =IFERROR(VLOOKUP($E4,Features!$A$2:$Q$74,6,FALSE),"") | G4: =IFERROR(VLOOKUP($E4,Features!$A$2:$Q$74,15,FALSE),"")
A5: IMP-02 | B5: Impayés | C5: Relances échelonnées | D5: MVP | E5: F30 | F5: =IFERROR(VLOOKUP($E5,Features!$A$2:$Q$74,6,FALSE),"") | G5: =IFERROR(VLOOKUP($E5,Features!$A$2:$Q$74,15,FALSE),"")
A6: IMP-03 | B6: Impayés | C6: Promesse de paiement | D6: MVP | E6: F30 | F6: =IFERROR(VLOOKUP($E6,Features!$A$2:$Q$74,6,FALSE),"") | G6: =IFERROR(VLOOKUP($E6,Features!$A$2:$Q$74,15,FALSE),"")
A7: NOT-01 | B7: Notifications | C7: Moteur de notifications | D7: MVP | E7: F26 | F7: =IFERROR(VLOOKUP($E7,Features!$A$2:$Q$74,6,FALSE),"") | G7: =IFERROR(VLOOKUP($E7,Features!$A$2:$Q$74,15,FALSE),"")
A8: NOT-02 | B8: Notifications | C8: Modèles | D8: MVP | E8: F26 | F8: =IFERROR(VLOOKUP($E8,Features!$A$2:$Q$74,6,FALSE),"") | G8: =IFERROR(VLOOKUP($E8,Features!$A$2:$Q$74,15,FALSE),"")
A9: NOT-03 | B9: Notifications | C9: Règles financières | D9: MVP | E9: F27 | F9: =IFERROR(VLOOKUP($E9,Features!$A$2:$Q$74,6,FALSE),"") | G9: =IFERROR(VLOOKUP($E9,Features!$A$2:$Q$74,15,FALSE),"")
A10: NOT-04 | B10: Notifications | C10: Règles planning | D10: MVP | E10: F28 | F10: =IFERROR(VLOOKUP($E10,Features!$A$2:$Q$74,6,FALSE),"") | G10: =IFERROR(VLOOKUP($E10,Features!$A$2:$Q$74,15,FALSE),"")
A11: NOT-06 | B11: Notifications | C11: Consentements et canaux | D11: MVP | E11: F26 | F11: =IFERROR(VLOOKUP($E11,Features!$A$2:$Q$74,6,FALSE),"") | G11: =IFERROR(VLOOKUP($E11,Features!$A$2:$Q$74,15,FALSE),"")
A12: NOT-07 | B12: Notifications | C12: Journal des envois | D12: MVP | E12: F26 | F12: =IFERROR(VLOOKUP($E12,Features!$A$2:$Q$74,6,FALSE),"") | G12: =IFERROR(VLOOKUP($E12,Features!$A$2:$Q$74,15,FALSE),"")
A13: NOT-08 | B13: Notifications | C13: Autres règles | D13: V2 | E13: F27 | F13: =IFERROR(VLOOKUP($E13,Features!$A$2:$Q$74,6,FALSE),"") | G13: =IFERROR(VLOOKUP($E13,Features!$A$2:$Q$74,15,FALSE),"")
... A24: EVT-08 | B24: Camp d'été et fin d'année | C24: Annonce de masse aux parents | D24: MVP | E24: F29 | F24: =IFERROR(VLOOKUP($E24,Features!$A$2:$Q$74,6,FALSE),"") | G24: =IFERROR(VLOOKUP($E24,Features!$A$2:$Q$74,15,FALSE),"")
A26: R3 — Parents, relances et exports comptables

Sheet R4
A1: ID | B1: Domaine | C1: Libellé | D1: Cahier | E1: Feature | F1: État | G1: Date production
A2: RES-04 | B2: Réservations | C2: Séance à l'unité / carnet | D2: MVP | E2: F37 | F2: =IFERROR(VLOOKUP($E2,Features!$A$2:$Q$74,6,FALSE),"") | G2: =IFERROR(VLOOKUP($E2,Features!$A$2:$Q$74,15,FALSE),"")
A3: PRE-01 | B3: Présences | C3: Appel par le coach | D3: MVP | E3: F35 | F3: =IFERROR(VLOOKUP($E3,Features!$A$2:$Q$74,6,FALSE),"") | G3: =IFERROR(VLOOKUP($E3,Features!$A$2:$Q$74,15,FALSE),"")
A4: PRE-02 | B4: Présences | C4: Pointage accueil | D4: MVP | E4: F36 | F4: =IFERROR(VLOOKUP($E4,Features!$A$2:$Q$74,6,FALSE),"") | G4: =IFERROR(VLOOKUP($E4,Features!$A$2:$Q$74,15,FALSE),"")
A5: PRE-03 | B5: Présences | C5: Statut administratif au pointage | D5: MVP | E5: F36 | F5: =IFERROR(VLOOKUP($E5,Features!$A$2:$Q$74,6,FALSE),"") | G5: =IFERROR(VLOOKUP($E5,Features!$A$2:$Q$74,15,FALSE),"")
A6: PRE-04 | B6: Présences | C6: Vue temps réel | D6: MVP | E6: F38 | F6: =IFERROR(VLOOKUP($E6,Features!$A$2:$Q$74,6,FALSE),"") | G6: =IFERROR(VLOOKUP($E6,Features!$A$2:$Q$74,15,FALSE),"")
A7: PRE-06 | B7: Présences | C7: Sortie de l'enfant | D7: V2 | E7: F40 | F7: =IFERROR(VLOOKUP($E7,Features!$A$2:$Q$74,6,FALSE),"") | G7: =IFERROR(VLOOKUP($E7,Features!$A$2:$Q$74,15,FALSE),"")
A8: PRE-07 | B8: Présences | C8: Historique et assiduité | D8: MVP | E8: F39 | F8: =IFERROR(VLOOKUP($E8,Features!$A$2:$Q$74,6,FALSE),"") | G8: =IFERROR(VLOOKUP($E8,Features!$A$2:$Q$74,15,FALSE),"")
A9: PRE-08 | B9: Présences | C9: Mode hors ligne | D9: V2 | E9: F35 | F9: =IFERROR(VLOOKUP($E9,Features!$A$2:$Q$74,6,FALSE),"") | G9: =IFERROR(VLOOKUP($E9,Features!$A$2:$Q$74,15,FALSE),"")
A10: IMP-05 | B10: Impayés | C10: Politique d'accès | D10: MVP | E10: F36 | F10: =IFERROR(VLOOKUP($E10,Features!$A$2:$Q$74,6,FALSE),"") | G10: =IFERROR(VLOOKUP($E10,Features!$A$2:$Q$74,15,FALSE),"")
A11: NOT-05 | B11: Notifications | C11: Règles présence | D11: V2 | E11: F41 | F11: =IFERROR(VLOOKUP($E11,Features!$A$2:$Q$74,6,FALSE),"") | G11: =IFERROR(VLOOKUP($E11,Features!$A$2:$Q$74,15,FALSE),"")
A12: COA-04 | B12: Coachs | C12: Séances réalisées | D12: MVP | E12: F39 | F12: =IFERROR(VLOOKUP($E12,Features!$A$2:$Q$74,6,FALSE),"") | G12: =IFERROR(VLOOKUP($E12,Features!$A$2:$Q$74,15,FALSE),"")
A13: REP-01 | B13: Reporting | C13: Tableau de bord opérationnel | D13: MVP | E13: F38 | F13: =IFERROR(VLOOKUP($E13,Features!$A$2:$Q$74,6,FALSE),"") | G13: =IFERROR(VLOOKUP($E13,Features!$A$2:$Q$74,15,FALSE),"")
... A17: SEC-06 | B17: Sécurité | C17: Durées de conservation | D17: V2 | E17: F42 | F17: =IFERROR(VLOOKUP($E17,Features!$A$2:$Q$74,6,FALSE),"") | G17: =IFERROR(VLOOKUP($E17,Features!$A$2:$Q$74,15,FALSE),"")
A19: R4 — Pointage

Sheet R5
A1: ID | B1: Domaine | C1: Libellé | D1: Cahier | E1: Feature | F1: État | G1: Date production
A2: TAR-07 | B2: Tarification | C2: Codes promo | D2: V2 | E2: F49 | F2: =IFERROR(VLOOKUP($E2,Features!$A$2:$Q$74,6,FALSE),"") | G2: =IFERROR(VLOOKUP($E2,Features!$A$2:$Q$74,15,FALSE),"")
A3: IMP-04 | B3: Impayés | C3: Tâche de recouvrement | D3: V2 | E3: F47 | F3: =IFERROR(VLOOKUP($E3,Features!$A$2:$Q$74,6,FALSE),"") | G3: =IFERROR(VLOOKUP($E3,Features!$A$2:$Q$74,15,FALSE),"")
A4: COA-02 | B4: Coachs | C4: Disponibilités et absences | D4: V2 | E4: F46 | F4: =IFERROR(VLOOKUP($E4,Features!$A$2:$Q$74,6,FALSE),"") | G4: =IFERROR(VLOOKUP($E4,Features!$A$2:$Q$74,15,FALSE),"")
A5: REM-01 | B5: Rémunération | C5: Modèles de rémunération | D5: V2 | E5: F43 | F5: =IFERROR(VLOOKUP($E5,Features!$A$2:$Q$74,6,FALSE),"") | G5: =IFERROR(VLOOKUP($E5,Features!$A$2:$Q$74,15,FALSE),"")
A6: REM-02 | B6: Rémunération | C6: État mensuel | D6: V2 | E6: F44 | F6: =IFERROR(VLOOKUP($E6,Features!$A$2:$Q$74,6,FALSE),"") | G6: =IFERROR(VLOOKUP($E6,Features!$A$2:$Q$74,15,FALSE),"")
A7: REM-03 | B7: Rémunération | C7: Avances | D7: V2 | E7: F44 | F7: =IFERROR(VLOOKUP($E7,Features!$A$2:$Q$74,6,FALSE),"") | G7: =IFERROR(VLOOKUP($E7,Features!$A$2:$Q$74,15,FALSE),"")
A8: REM-04 | B8: Rémunération | C8: Paiement de la rémunération | D8: V2 | E8: F44 | F8: =IFERROR(VLOOKUP($E8,Features!$A$2:$Q$74,6,FALSE),"") | G8: =IFERROR(VLOOKUP($E8,Features!$A$2:$Q$74,15,FALSE),"")
A9: REM-05 | B9: Rémunération | C9: Export pour la paie | D9: V2 | E9: F44 | F9: =IFERROR(VLOOKUP($E9,Features!$A$2:$Q$74,6,FALSE),"") | G9: =IFERROR(VLOOKUP($E9,Features!$A$2:$Q$74,15,FALSE),"")
A10: PER-01 | B10: Personnel administratif | C10: Fiche personnel et prestataires | D10: V2 | E10: F45 | F10: =IFERROR(VLOOKUP($E10,Features!$A$2:$Q$74,6,FALSE),"") | G10: =IFERROR(VLOOKUP($E10,Features!$A$2:$Q$74,15,FALSE),"")
A11: PER-02 | B11: Personnel administratif | C11: Dépenses récurrentes | D11: V2 | E11: F45 | F11: =IFERROR(VLOOKUP($E11,Features!$A$2:$Q$74,6,FALSE),"") | G11: =IFERROR(VLOOKUP($E11,Features!$A$2:$Q$74,15,FALSE),"")
A12: PER-03 | B12: Personnel administratif | C12: Tâches | D12: V2 | E12: F47 | F12: =IFERROR(VLOOKUP($E12,Features!$A$2:$Q$74,6,FALSE),"") | G12: =IFERROR(VLOOKUP($E12,Features!$A$2:$Q$74,15,FALSE),"")
A13: POS-03 | B13: POS | C13: Retour et échange | D13: V2 | E13: F49 | F13: =IFERROR(VLOOKUP($E13,Features!$A$2:$Q$74,6,FALSE),"") | G13: =IFERROR(VLOOKUP($E13,Features!$A$2:$Q$74,15,FALSE),"")
... A19: ADM-05 | B19: Administration | C19: Règles d'automatisation | D19: V2 | E19: F47 | F19: =IFERROR(VLOOKUP($E19,Features!$A$2:$Q$74,6,FALSE),"") | G19: =IFERROR(VLOOKUP($E19,Features!$A$2:$Q$74,15,FALSE),"")
A21: R5 — Rémunération et arrière-boutique

Sheet R6
A1: ID | B1: Domaine | C1: Libellé | D1: Cahier | E1: Feature | F1: État | G1: Date production
A2: FAM-14 | B2: Familles / Adhérents | C2: Fusion de doublons | D2: V2 | E2: F56 | F2: =IFERROR(VLOOKUP($E2,Features!$A$2:$Q$74,6,FALSE),"") | G2: =IFERROR(VLOOKUP($E2,Features!$A$2:$Q$74,15,FALSE),"")
A3: NIV-02 | B3: Niveaux | C3: Référentiel de compétences | D3: V2 | E3: F50 | F3: =IFERROR(VLOOKUP($E3,Features!$A$2:$Q$74,6,FALSE),"") | G3: =IFERROR(VLOOKUP($E3,Features!$A$2:$Q$74,15,FALSE),"")
A4: NIV-03 | B4: Niveaux | C4: Évaluation | D4: V2 | E4: F50 | F4: =IFERROR(VLOOKUP($E4,Features!$A$2:$Q$74,6,FALSE),"") | G4: =IFERROR(VLOOKUP($E4,Features!$A$2:$Q$74,15,FALSE),"")
A5: NIV-04 | B5: Niveaux | C5: Critères de passage | D5: V2 | E5: F51 | F5: =IFERROR(VLOOKUP($E5,Features!$A$2:$Q$74,6,FALSE),"") | G5: =IFERROR(VLOOKUP($E5,Features!$A$2:$Q$74,15,FALSE),"")
A6: NIV-05 | B6: Niveaux | C6: Passage de niveau | D6: V2 | E6: F51 | F6: =IFERROR(VLOOKUP($E6,Features!$A$2:$Q$74,6,FALSE),"") | G6: =IFERROR(VLOOKUP($E6,Features!$A$2:$Q$74,15,FALSE),"")
A7: RES-02 | B7: Réservations | C7: Liste d'attente par groupe | D7: V2 | E7: F54 | F7: =IFERROR(VLOOKUP($E7,Features!$A$2:$Q$74,6,FALSE),"") | G7: =IFERROR(VLOOKUP($E7,Features!$A$2:$Q$74,15,FALSE),"")
A8: RES-03 | B8: Réservations | C8: Place réservée | D8: V2 | E8: F54 | F8: =IFERROR(VLOOKUP($E8,Features!$A$2:$Q$74,6,FALSE),"") | G8: =IFERROR(VLOOKUP($E8,Features!$A$2:$Q$74,15,FALSE),"")
A9: INS-05 | B9: Abonnements / Inscriptions | C9: Réinscription de saison | D9: V2 | E9: F53 | F9: =IFERROR(VLOOKUP($E9,Features!$A$2:$Q$74,6,FALSE),"") | G9: =IFERROR(VLOOKUP($E9,Features!$A$2:$Q$74,15,FALSE),"")
A10: INS-06 | B10: Abonnements / Inscriptions | C10: Pause | D10: V2 | E10: F55 | F10: =IFERROR(VLOOKUP($E10,Features!$A$2:$Q$74,6,FALSE),"") | G10: =IFERROR(VLOOKUP($E10,Features!$A$2:$Q$74,15,FALSE),"")
A11: REP-04 | B11: Reporting | C11: Rapports standard | D11: V2 | E11: F57 | F11: =IFERROR(VLOOKUP($E11,Features!$A$2:$Q$74,6,FALSE),"") | G11: =IFERROR(VLOOKUP($E11,Features!$A$2:$Q$74,15,FALSE),"")
A12: MKT-03 | B12: Marketing | C12: Relance des anciens | D12: V2 | E12: F53 | F12: =IFERROR(VLOOKUP($E12,Features!$A$2:$Q$74,6,FALSE),"") | G12: =IFERROR(VLOOKUP($E12,Features!$A$2:$Q$74,15,FALSE),"")
A13: APC-04 | B13: Application coach | C13: Évaluations | D13: V2 | E13: F50 | F13: =IFERROR(VLOOKUP($E13,Features!$A$2:$Q$74,6,FALSE),"") | G13: =IFERROR(VLOOKUP($E13,Features!$A$2:$Q$74,15,FALSE),"")
A14: EVT-07 | B14: Camp d'été et fin d'année | C14: Certificats et diplômes sportifs | D14: V2 | E14: F52 | F14: =IFERROR(VLOOKUP($E14,Features!$A$2:$Q$74,6,FALSE),"") | G14: =IFERROR(VLOOKUP($E14,Features!$A$2:$Q$74,15,FALSE),"")
A16: R6 — Fin de saison et réinscription

Sheet R7
A1: ID | B1: Domaine | C1: Libellé | D1: Cahier | E1: Feature | F1: État | G1: Date production
A2: RES-07 | B2: Réservations | C2: Stages et événements | D2: V2 | E2: F60 | F2: =IFERROR(VLOOKUP($E2,Features!$A$2:$Q$74,6,FALSE),"") | G2: =IFERROR(VLOOKUP($E2,Features!$A$2:$Q$74,15,FALSE),"")
A3: EVT-01 | B3: Camp d'été et fin d'année | C3: Programme de camp | D3: V2 | E3: F58 | F3: =IFERROR(VLOOKUP($E3,Features!$A$2:$Q$74,6,FALSE),"") | G3: =IFERROR(VLOOKUP($E3,Features!$A$2:$Q$74,15,FALSE),"")
A4: EVT-02 | B4: Camp d'été et fin d'année | C4: Emploi du temps journalier | D4: V2 | E4: F58 | F4: =IFERROR(VLOOKUP($E4,Features!$A$2:$Q$74,6,FALSE),"") | G4: =IFERROR(VLOOKUP($E4,Features!$A$2:$Q$74,15,FALSE),"")
A5: EVT-03 | B5: Camp d'été et fin d'année | C5: Inscription au camp, adhérent ou non | D5: V2 | E5: F60 | F5: =IFERROR(VLOOKUP($E5,Features!$A$2:$Q$74,6,FALSE),"") | G5: =IFERROR(VLOOKUP($E5,Features!$A$2:$Q$74,15,FALSE),"")
A6: EVT-04 | B6: Camp d'été et fin d'année | C6: Tarif du camp | D6: V2 | E6: F59 | F6: =IFERROR(VLOOKUP($E6,Features!$A$2:$Q$74,6,FALSE),"") | G6: =IFERROR(VLOOKUP($E6,Features!$A$2:$Q$74,15,FALSE),"")
A7: EVT-05 | B7: Camp d'été et fin d'année | C7: Journée continue | D7: V2 | E7: F61 | F7: =IFERROR(VLOOKUP($E7,Features!$A$2:$Q$74,6,FALSE),"") | G7: =IFERROR(VLOOKUP($E7,Features!$A$2:$Q$74,15,FALSE),"")
A9: R7 — Camp d'été

Sheet R8
A1: ID | B1: Domaine | C1: Libellé | D1: Cahier | E1: Feature | F1: État | G1: Date production
A2: CRM-01 | B2: CRM / Prospects | C2: Fiche prospect | D2: V2 | E2: F68 | F2: =IFERROR(VLOOKUP($E2,Features!$A$2:$Q$74,6,FALSE),"") | G2: =IFERROR(VLOOKUP($E2,Features!$A$2:$Q$74,15,FALSE),"")
A3: CRM-02 | B3: CRM / Prospects | C3: Entonnoir à étapes | D3: V2 | E3: F68 | F3: =IFERROR(VLOOKUP($E3,Features!$A$2:$Q$74,6,FALSE),"") | G3: =IFERROR(VLOOKUP($E3,Features!$A$2:$Q$74,15,FALSE),"")
A4: CRM-03 | B4: CRM / Prospects | C4: Conversion en famille | D4: V2 | E4: F68 | F4: =IFERROR(VLOOKUP($E4,Features!$A$2:$Q$74,6,FALSE),"") | G4: =IFERROR(VLOOKUP($E4,Features!$A$2:$Q$74,15,FALSE),"")
A5: CRM-04 | B5: CRM / Prospects | C5: Formulaire de contact public | D5: V2 | E5: F68 | F5: =IFERROR(VLOOKUP($E5,Features!$A$2:$Q$74,6,FALSE),"") | G5: =IFERROR(VLOOKUP($E5,Features!$A$2:$Q$74,15,FALSE),"")
A6: CRM-05 | B6: CRM / Prospects | C6: Relances automatiques | D6: V2 | E6: F68 | F6: =IFERROR(VLOOKUP($E6,Features!$A$2:$Q$74,6,FALSE),"") | G6: =IFERROR(VLOOKUP($E6,Features!$A$2:$Q$74,15,FALSE),"")
A7: ONB-02 | B7: Onboarding | C7: Saisie par le parent | D7: V2 | E7: F65 | F7: =IFERROR(VLOOKUP($E7,Features!$A$2:$Q$74,6,FALSE),"") | G7: =IFERROR(VLOOKUP($E7,Features!$A$2:$Q$74,15,FALSE),"")
A8: RES-05 | B8: Réservations | C8: Rattrapage | D8: V2 | E8: F65 | F8: =IFERROR(VLOOKUP($E8,Features!$A$2:$Q$74,6,FALSE),"") | G8: =IFERROR(VLOOKUP($E8,Features!$A$2:$Q$74,15,FALSE),"")
A9: PRE-05 | B9: Présences | C9: Absence déclarée | D9: V2 | E9: F65 | F9: =IFERROR(VLOOKUP($E9,Features!$A$2:$Q$74,6,FALSE),"") | G9: =IFERROR(VLOOKUP($E9,Features!$A$2:$Q$74,15,FALSE),"")
A10: FAC-10 | B10: Paiements | C10: Lien de paiement en ligne | D10: V2 | E10: F63 | F10: =IFERROR(VLOOKUP($E10,Features!$A$2:$Q$74,6,FALSE),"") | G10: =IFERROR(VLOOKUP($E10,Features!$A$2:$Q$74,15,FALSE),"")
A11: COM-03 | B11: Communication parents | C11: Annonces | D11: V2 | E11: F67 | F11: =IFERROR(VLOOKUP($E11,Features!$A$2:$Q$74,6,FALSE),"") | G11: =IFERROR(VLOOKUP($E11,Features!$A$2:$Q$74,15,FALSE),"")
A12: COM-04 | B12: Communication parents | C12: Message du coach | D12: V2 | E12: F67 | F12: =IFERROR(VLOOKUP($E12,Features!$A$2:$Q$74,6,FALSE),"") | G12: =IFERROR(VLOOKUP($E12,Features!$A$2:$Q$74,15,FALSE),"")
A13: MKT-01 | B13: Marketing | C13: Campagnes WhatsApp / SMS / email | D13: V2 | E13: F69 | F13: =IFERROR(VLOOKUP($E13,Features!$A$2:$Q$74,6,FALSE),"") | G13: =IFERROR(VLOOKUP($E13,Features!$A$2:$Q$74,15,FALSE),"")
... A21: PLT-08 | B21: Multi-clubs / multi-sites | C21: Langues | D21: V2 | E21: F70 | F21: =IFERROR(VLOOKUP($E21,Features!$A$2:$Q$74,6,FALSE),"") | G21: =IFERROR(VLOOKUP($E21,Features!$A$2:$Q$74,15,FALSE),"")
A23: R8 — Portail parent et acquisition

Sheet R9
A1: ID | B1: Domaine | C1: Libellé | D1: Cahier | E1: Feature | F1: État | G1: Date production
A2: ADM-02 | B2: Administration | C2: Assistant de démarrage | D2: MVP | E2: F71 | F2: =IFERROR(VLOOKUP($E2,Features!$A$2:$Q$74,6,FALSE),"") | G2: =IFERROR(VLOOKUP($E2,Features!$A$2:$Q$74,15,FALSE),"")
A3: ADM-03 | B3: Administration | C3: Champs personnalisés | D3: V2 | E3: F71 | F3: =IFERROR(VLOOKUP($E3,Features!$A$2:$Q$74,6,FALSE),"") | G3: =IFERROR(VLOOKUP($E3,Features!$A$2:$Q$74,15,FALSE),"")
A4: PLT-02 | B4: Multi-clubs / multi-sites | C4: Utilisateur multi-clubs | D4: MVP | E4: F72 | F4: =IFERROR(VLOOKUP($E4,Features!$A$2:$Q$74,6,FALSE),"") | G4: =IFERROR(VLOOKUP($E4,Features!$A$2:$Q$74,15,FALSE),"")
A5: PLT-07 | B5: Multi-clubs / multi-sites | C5: Abonnement SaaS | D5: V2 | E5: F73 | F5: =IFERROR(VLOOKUP($E5,Features!$A$2:$Q$74,6,FALSE),"") | G5: =IFERROR(VLOOKUP($E5,Features!$A$2:$Q$74,15,FALSE),"")
A7: R9 — Deuxième club

Sheet Écartés
A1: ID | B1: Domaine | C1: Libellé | D1: Cahier | E1: Feature | F1: État | G1: Date production
A2: STK-04 | B2: Stock | C2: Inventaire | D2: V3 | E2: Écartés | F2: =IFERROR(VLOOKUP($E2,Features!$A$2:$Q$74,6,FALSE),"") | G2: =IFERROR(VLOOKUP($E2,Features!$A$2:$Q$74,15,FALSE),"")
A3: STK-05 | B3: Stock | C3: Coût d'achat, marge, fournisseurs | D3: V3 | E3: Écartés | F3: =IFERROR(VLOOKUP($E3,Features!$A$2:$Q$74,6,FALSE),"") | G3: =IFERROR(VLOOKUP($E3,Features!$A$2:$Q$74,15,FALSE),"")
A4: FIN-06 | B4: Finance | C4: Rapprochement bancaire | D4: V3 | E4: Écartés | F4: =IFERROR(VLOOKUP($E4,Features!$A$2:$Q$74,6,FALSE),"") | G4: =IFERROR(VLOOKUP($E4,Features!$A$2:$Q$74,15,FALSE),"")
A5: FIN-07 | B5: Finance | C5: Produits constatés d'avance | D5: V3 | E5: Écartés | F5: =IFERROR(VLOOKUP($E5,Features!$A$2:$Q$74,6,FALSE),"") | G5: =IFERROR(VLOOKUP($E5,Features!$A$2:$Q$74,15,FALSE),"")
A6: CPT-05 | B6: Comptabilité | C6: Format de facture structuré | D6: V3 | E6: Écartés | F6: =IFERROR(VLOOKUP($E6,Features!$A$2:$Q$74,6,FALSE),"") | G6: =IFERROR(VLOOKUP($E6,Features!$A$2:$Q$74,15,FALSE),"")
A7: REP-06 | B7: Reporting | C7: Rétention | D7: V3 | E7: Écartés | F7: =IFERROR(VLOOKUP($E7,Features!$A$2:$Q$74,6,FALSE),"") | G7: =IFERROR(VLOOKUP($E7,Features!$A$2:$Q$74,15,FALSE),"")
A8: MKT-02 | B8: Marketing | C8: Parrainage | D8: V3 | E8: Écartés | F8: =IFERROR(VLOOKUP($E8,Features!$A$2:$Q$74,6,FALSE),"") | G8: =IFERROR(VLOOKUP($E8,Features!$A$2:$Q$74,15,FALSE),"")
A9: MKT-04 | B9: Marketing | C9: Aide à la rédaction par IA | D9: V3 | E9: Écartés | F9: =IFERROR(VLOOKUP($E9,Features!$A$2:$Q$74,6,FALSE),"") | G9: =IFERROR(VLOOKUP($E9,Features!$A$2:$Q$74,15,FALSE),"")
A10: APP-07 | B10: Application parent | C10: Application native et push | D10: V3 | E10: Écartés | F10: =IFERROR(VLOOKUP($E10,Features!$A$2:$Q$74,6,FALSE),"") | G10: =IFERROR(VLOOKUP($E10,Features!$A$2:$Q$74,15,FALSE),"")
A11: INT-04 | B11: API / Intégrations | C11: API publique et webhooks | D11: V3 | E11: Écartés | F11: =IFERROR(VLOOKUP($E11,Features!$A$2:$Q$74,6,FALSE),"") | G11: =IFERROR(VLOOKUP($E11,Features!$A$2:$Q$74,15,FALSE),"")
A12: INT-05 | B12: API / Intégrations | C12: Calendrier | D12: V3 | E12: Écartés | F12: =IFERROR(VLOOKUP($E12,Features!$A$2:$Q$74,6,FALSE),"") | G12: =IFERROR(VLOOKUP($E12,Features!$A$2:$Q$74,15,FALSE),"")
A13: PLT-03 | B13: Multi-clubs / multi-sites | C13: Sites | D13: V3 | E13: Écartés | F13: =IFERROR(VLOOKUP($E13,Features!$A$2:$Q$74,6,FALSE),"") | G13: =IFERROR(VLOOKUP($E13,Features!$A$2:$Q$74,15,FALSE),"")
A14: PLT-06 | B14: Multi-clubs / multi-sites | C14: Consolidation multi-sites | D14: V3 | E14: Écartés | F14: =IFERROR(VLOOKUP($E14,Features!$A$2:$Q$74,6,FALSE),"") | G14: =IFERROR(VLOOKUP($E14,Features!$A$2:$Q$74,15,FALSE),"")
A16: Hors du plan de releases
